prettierfier/__init__.py
prettierfier/prettierfier.py
prettierfier-1.0.3.dist-info/LICENSE
prettierfier-1.0.3.dist-info/METADATA
prettierfier-1.0.3.dist-info/WHEEL
prettierfier-1.0.3.dist-info/top_level.txt
prettierfier-1.0.3.dist-info/RECORD
