Metadata-Version: 2.1
Name: prettierfier
Version: 1.0.3
Summary: Intelligently pretty-print HTML/XML with inline tags.
Home-page: https://github.com/annedo/prettierfier
Author: Anne Do
Author-email: anne.do.designs@gmail.com
License: MIT
Keywords: html xml formatting prettify
Platform: UNKNOWN
Classifier: Programming Language :: Python :: 3
Classifier: License :: OSI Approved :: MIT License
Classifier: Operating System :: Microsoft :: Windows
Classifier: Intended Audience :: Developers
Classifier: Natural Language :: English
Classifier: Programming Language :: Python :: 3.7
Classifier: Topic :: Text Processing :: Markup :: HTML
Classifier: Topic :: Text Processing :: Markup :: XML
